clustercomputers/__init__.py
clustercomputers/_util.py
clustercomputers/aclient.py
clustercomputers/error.py
clustercomputers/item.py
clustercomputers/py.typed
clustercomputers/redstone.py
clustercomputers/sclient.py
clustercomputers/sensor.py
clustercomputers/sound.py
clustercomputers/world.py
clustercomputers/_proto/__init__.py
clustercomputers/_proto/buf/__init__.py
clustercomputers/_proto/buf/validate/__init__.py
clustercomputers/_proto/buf/validate/validate_pb2.py
clustercomputers/_proto/buf/validate/validate_pb2.pyi
clustercomputers/_proto/clustercomputers/__init__.py
clustercomputers/_proto/clustercomputers/world/__init__.py
clustercomputers/_proto/clustercomputers/world/actions/__init__.py
clustercomputers/_proto/clustercomputers/world/actions/drop_item_pb2.py
clustercomputers/_proto/clustercomputers/world/actions/drop_item_pb2.pyi
clustercomputers/_proto/clustercomputers/world/actions/drop_item_result_pb2.py
clustercomputers/_proto/clustercomputers/world/actions/drop_item_result_pb2.pyi
clustercomputers/_proto/clustercomputers/world/actions/get_inventory_pb2.py
clustercomputers/_proto/clustercomputers/world/actions/get_inventory_pb2.pyi
clustercomputers/_proto/clustercomputers/world/actions/get_location_pb2.py
clustercomputers/_proto/clustercomputers/world/actions/get_location_pb2.pyi
clustercomputers/_proto/clustercomputers/world/actions/get_redstone_inputs_pb2.py
clustercomputers/_proto/clustercomputers/world/actions/get_redstone_inputs_pb2.pyi
clustercomputers/_proto/clustercomputers/world/actions/get_redstone_outputs_pb2.py
clustercomputers/_proto/clustercomputers/world/actions/get_redstone_outputs_pb2.pyi
clustercomputers/_proto/clustercomputers/world/actions/indexed_world_result_pb2.py
clustercomputers/_proto/clustercomputers/world/actions/indexed_world_result_pb2.pyi
clustercomputers/_proto/clustercomputers/world/actions/merge_item_pb2.py
clustercomputers/_proto/clustercomputers/world/actions/merge_item_pb2.pyi
clustercomputers-0.3.0.dist-info/licenses/LICENSE
clustercomputers-0.3.0.dist-info/licenses/NOTICE
clustercomputers-0.3.0.dist-info/METADATA
clustercomputers-0.3.0.dist-info/WHEEL
clustercomputers-0.3.0.dist-info/top_level.txt
clustercomputers-0.3.0.dist-info/RECORD
