Metadata-Version: 2.4
Name: clustercomputers
Version: 0.3.0
Summary: Python API and CLI tool for the ClusterComputers Minecraft mod
Author: Adralioh
License-Expression: Apache-2.0
Project-URL: Source, https://gitlab.com/clustercomputers/python
Keywords: minecraft,mod,kubernetes,clustercomputers
Classifier: Development Status :: 3 - Alpha
Classifier: Framework :: Sphinx
Classifier: Intended Audience :: Developers
Classifier: Operating System :: OS Independent
Classifier: Programming Language :: Python :: 3
Classifier: Topic :: Games/Entertainment
Classifier: Typing :: Typed
Requires-Python: >=3.13
License-File: LICENSE
License-File: NOTICE
Requires-Dist: protobuf~=6.31.1
Requires-Dist: grpcio~=1.74
Dynamic: license-file
